rekonify/__init__.py
rekonify/__version__.py
rekonify/client.py
rekonify/constants.py
rekonify/exceptions.py
rekonify/models.py
rekonify/utils.py
rekonify_python_sdk-2.1.4.dist-info/licenses/LICENSE
rekonify_python_sdk-2.1.4.dist-info/METADATA
rekonify_python_sdk-2.1.4.dist-info/WHEEL
rekonify_python_sdk-2.1.4.dist-info/top_level.txt
rekonify_python_sdk-2.1.4.dist-info/RECORD
