Metadata-Version: 2.4
Name: rekonify-python-sdk
Version: 2.1.4
Summary: The Rekonify Python SDK is the official client for seamless, async-ready integration with the Rekonify API, streamlining transaction ingestion
Home-page: https://github.com/Frndz-org/rekonify-python-sdk
Download-URL: https://github.com/Frndz-org/rekonify-python-sdk/archive/refs/tags/2.1.4.tar.gz
Author: Kuadey Elikem Yao
Author-email: Kuadey Elikem Yao <key@rekonify.com>
License-Expression: MIT
Project-URL: Homepage, https://github.com/Frndz-org/rekonify-python-sdk
Project-URL: Bug Tracker, https://github.com/Frndz-org/rekonify-python-sdk/issues
Keywords: rekonify,reconciliation,finance,transactions,payment,automation,sdk,api-client,async,event-tracking,financial-data,accounting,python-sdk,transaction-matching,integration,pay-in,payout,erp,banking,data-ingestion
Classifier: Development Status :: 5 - Production/Stable
Classifier: Programming Language :: Python
Classifier: Programming Language :: Python :: 3
Classifier: Programming Language :: Python :: 3.11
Classifier: Programming Language :: Python :: 3.12
Classifier: Environment :: Web Environment
Classifier: Intended Audience :: Developers
Classifier: Intended Audience :: Financial and Insurance Industry
Classifier: Operating System :: OS Independent
Requires-Python: >=3.10.8
License-File: LICENSE
Requires-Dist: requests
Requires-Dist: pydantic[email]
Requires-Dist: pydantic
Requires-Dist: tenacity
Provides-Extra: dev
Requires-Dist: pytest>=3.7; extra == "dev"
Requires-Dist: check-manifest; extra == "dev"
Requires-Dist: twine; extra == "dev"
Dynamic: author
Dynamic: download-url
Dynamic: home-page
Dynamic: license-file
Dynamic: requires-python
